escape_cli/__init__.py
escape_cli/commands/__init__.py
escape_cli/commands/cover.py
escape_cli/commands/discover.py
escape_cli/commands/init.py
escape_cli/commands/scan.py
escape_cli/executor/__init__.py
escape_cli/executor/execute.py
escape_cli/helpers/__init__.py
escape_cli/main.py
escape_cli/middlewares/__init__.py
escape_cli/middlewares/django.py
escape_cli/middlewares/flask.py
escape_cli/patchs/__init__.py
escape_cli/patchs/django.py
escape_cli/patchs/flask.py
escape_cli/static/__init__.py
escape_cli/static/command_options.py
escape_cli/static/constants.py
escape_cli/static/supported-libs.json
escape_cli/utils/__init__.py
escape_cli/utils/commands.py
escape_cli/utils/config.py
escape_cli/utils/coverage.py
escape_cli/utils/http.py
escape_cli/utils/logs_formatter.py
escape_cli/utils/parse.py
escape_cli/utils/result.py
escape_cli/utils/sdk.py
escape_cli/utils/title.py
escape_cli/utils/vcs.py
escape_py-1.0.0b23.dist-info/entry_points.txt
escape_py-1.0.0b23.dist-info/WHEEL
escape_py-1.0.0b23.dist-info/METADATA
escape_py-1.0.0b23.dist-info/RECORD
