Metadata-Version: 2.1
Name: escape-py
Version: 1.0.0b23
Summary: Escape's Python CLI
Home-page: https://escape.tech/
License: Proprietary
Author: Escape Technologies SAS
Author-email: ping@escape.tech
Maintainer: Antoine Carossio
Maintainer-email: antoine.carossio@me.com
Requires-Python: >=3.6,<4.0
Classifier: License :: Other/Proprietary License
Classifier: Programming Language :: Python :: 3
Classifier: Programming Language :: Python :: 3.6
Classifier: Programming Language :: Python :: 3.7
Classifier: Programming Language :: Python :: 3.8
Classifier: Programming Language :: Python :: 3.9
Requires-Dist: Django (>=3.2,<4.0)
Requires-Dist: Flask (>=1.1.2,<2.0.0)
Requires-Dist: click (>=7.1.2,<8.0.0)
Requires-Dist: coverage (>=5.5,<6.0)
Requires-Dist: escape-scanner-darwin-x64 (>=1.0.0-beta.23,<2.0.0); sys_platform == "darwin"
Requires-Dist: escape-scanner-linux-x64 (>=1.0.0-beta.23,<2.0.0); sys_platform == "linux"
Requires-Dist: inquirer (>=2.7.0,<3.0.0)
Requires-Dist: loguru (>=0.5.3,<0.6.0)
Requires-Dist: requests (>=2.25.1,<3.0.0)
Requires-Dist: simplejson (>=3.17.2,<4.0.0)
Requires-Dist: termcolor (>=1.1.0,<2.0.0)
Project-URL: Bug Tracker, https://gitlab.com/escape.tech/product/issues
Project-URL: Repository, https://gitlab.com/escape.tech/product
